[
    {
        "table": "booking_agents",
        "columns": [
            "id",
            "name",
            "details"
        ]
    },
    {
        "table": "passengers",
        "columns": [
            "id",
            "first_name",
            "second_name",
            "last_name",
            "phone_number",
            "email_address",
            "address_lines",
            "city",
            "state_province_county",
            "country",
            "other_details"
        ]
    },
    {
        "table": "itinerary_reservations",
        "columns": [
            "id",
            "agent_id",
            "passenger_id",
            "reservation_status_code",
            "ticket_type_code",
            "travel_class_code",
            "date_reservation_made",
            "number_in_party"
        ]
    },
    {
        "table": "payments",
        "columns": [
            "id",
            "payment_status_code",
            "date",
            "amount"
        ]
    },
    {
        "table": "airports",
        "columns": [
            "code",
            "name",
            "location",
            "other_details"
        ]
    },
    {
        "table": "flight_schedules",
        "columns": [
            "flight_number",
            "airline_code",
            "usual_aircraft_type_code",
            "origin_airport_code",
            "destination_airport_code",
            "departure_date_time",
            "arrival_date_time"
        ]
    },
    {
        "table": "reservation_payments",
        "columns": [
            "reservation_id",
            "payment_id"
        ]
    },
    {
        "table": "legs",
        "columns": [
            "id",
            "flight_number",
            "origin_airport_code",
            "destination_airport_code",
            "actual_departure_time",
            "actual_arrival_time"
        ]
    },
    {
        "table": "calendar",
        "columns": [
            "day_date",
            "day_number",
            "business_day_yn"
        ]
    },
    {
        "table": "itinerary_legs",
        "columns": [
            "reservation_id",
            "leg_id"
        ]
    },
    {
        "table": "flight_costs",
        "columns": [
            "flight_number",
            "aircraft_type_code",
            "valid_from_date",
            "valid_to_date",
            "cost"
        ]
    }
]